wyxtest/__init__.py
wyxtest/q1.py
wyxtest-1.1.1.1.1.dist-info/METADATA
wyxtest-1.1.1.1.1.dist-info/RECORD
wyxtest-1.1.1.1.1.dist-info/WHEEL
wyxtest-1.1.1.1.1.dist-info/top_level.txt
wyxtest-1.1.1.1.1.dist-info/zip-safe
